linux_aio_bind/iocb.py
linux_aio_bind/iocb.pyi
linux_aio_bind/_syscall.pyi
linux_aio_bind/aio.py
linux_aio_bind/aio.pyi
linux_aio_bind/error.pyi
linux_aio_bind/__init__.py
linux_aio_bind/error.py
linux_aio_bind/_syscall.abi3.so
linux_aio_bind/syscall.py
linux_aio_bind-1.0.0.dist-info/top_level.txt
linux_aio_bind-1.0.0.dist-info/RECORD
linux_aio_bind-1.0.0.dist-info/METADATA
linux_aio_bind-1.0.0.dist-info/WHEEL
